{"files_in_context":[{"path":"backend/app/main.py","record_state":"stale","record_source":"read_tool","roo_read_date":1774953689621,"roo_edit_date":null,"user_edit_date":null},{"path":"frontend/src/components/ExcelTable.jsx","record_state":"active","record_source":"read_tool","roo_read_date":1774953708281,"roo_edit_date":null,"user_edit_date":null},{"path":"backend/app/reports.py","record_state":"stale","record_source":"read_tool","roo_read_date":1774953724280,"roo_edit_date":null,"user_edit_date":null},{"path":"frontend/src/components/ReportsPanel.jsx","record_state":"stale","record_source":"read_tool","roo_read_date":1774953737075,"roo_edit_date":null,"user_edit_date":null},{"path":"backend/app/reports.py","record_state":"stale","record_source":"roo_edited","roo_read_date":1774956951094,"roo_edit_date":1774956951094,"user_edit_date":null},{"path":"backend/app/reports.py","record_state":"active","record_source":"read_tool","roo_read_date":1774956962406,"roo_edit_date":1774956951094,"user_edit_date":null},{"path":"backend/app/models.py","record_state":"stale","record_source":"read_tool","roo_read_date":1774957596909,"roo_edit_date":null,"user_edit_date":null},{"path":"backend/app/schemas.py","record_state":"stale","record_source":"read_tool","roo_read_date":1774957619312,"roo_edit_date":null,"user_edit_date":null},{"path":"backend/app/models.py","record_state":"active","record_source":"roo_edited","roo_read_date":1774957663947,"roo_edit_date":1774957663947,"user_edit_date":null},{"path":"frontend/src/components/MasterPanel.jsx","record_state":"stale","record_source":"read_tool","roo_read_date":1774957679004,"roo_edit_date":null,"user_edit_date":null},{"path":"backend/app/schemas.py","record_state":"stale","record_source":"roo_edited","roo_read_date":1774957708717,"roo_edit_date":1774957708717,"user_edit_date":null},{"path":"backend/app/main.py","record_state":"stale","record_source":"roo_edited","roo_read_date":1774957753874,"roo_edit_date":1774957753874,"user_edit_date":null},{"path":"frontend/src/components/MasterPanel.jsx","record_state":"stale","record_source":"user_edited","roo_read_date":1774957679004,"roo_edit_date":null,"user_edit_date":1774957775790},{"path":"frontend/src/components/MasterPanel.jsx","record_state":"stale","record_source":"roo_edited","roo_read_date":1774957775879,"roo_edit_date":1774957775879,"user_edit_date":1774957775790},{"path":"frontend/src/components/MasterPanel.jsx","record_state":"stale","record_source":"roo_edited","roo_read_date":1774957795863,"roo_edit_date":1774957795863,"user_edit_date":1774957775790},{"path":"frontend/src/components/MasterPanel.jsx","record_state":"stale","record_source":"roo_edited","roo_read_date":1774957815654,"roo_edit_date":1774957815654,"user_edit_date":1774957775790},{"path":"frontend/src/components/MasterPanel.jsx","record_state":"stale","record_source":"roo_edited","roo_read_date":1774957841873,"roo_edit_date":1774957841873,"user_edit_date":1774957775790},{"path":"frontend/src/components/MasterPanel.jsx","record_state":"stale","record_source":"roo_edited","roo_read_date":1774957878505,"roo_edit_date":1774957878505,"user_edit_date":1774957775790},{"path":"frontend/src/components/MasterPanel.jsx","record_state":"stale","record_source":"read_tool","roo_read_date":1774958295005,"roo_edit_date":1774957878505,"user_edit_date":1774957775790},{"path":"frontend/src/components/MasterPanel.jsx","record_state":"active","record_source":"roo_edited","roo_read_date":1774958390384,"roo_edit_date":1774958390384,"user_edit_date":1774957775790},{"path":"frontend/src/components/ReportsPanel.jsx","record_state":"stale","record_source":"roo_edited","roo_read_date":1774958447087,"roo_edit_date":1774958447087,"user_edit_date":null},{"path":"frontend/src/components/ReportsPanel.jsx","record_state":"stale","record_source":"read_tool","roo_read_date":1774958466853,"roo_edit_date":1774958447087,"user_edit_date":null},{"path":"frontend/src/components/ReportsPanel.jsx","record_state":"stale","record_source":"roo_edited","roo_read_date":1774958541410,"roo_edit_date":1774958541410,"user_edit_date":null},{"path":"frontend/src/components/ReportsPanel.jsx","record_state":"stale","record_source":"roo_edited","roo_read_date":1774958590742,"roo_edit_date":1774958590742,"user_edit_date":null},{"path":"frontend/src/components/ReportsPanel.jsx","record_state":"stale","record_source":"roo_edited","roo_read_date":1774958615862,"roo_edit_date":1774958615862,"user_edit_date":null},{"path":"frontend/src/components/ReportsPanel.jsx","record_state":"stale","record_source":"user_edited","roo_read_date":1774958615862,"roo_edit_date":1774958615862,"user_edit_date":1774958687747},{"path":"frontend/src/components/ReportsPanel.jsx","record_state":"stale","record_source":"roo_edited","roo_read_date":1774958687887,"roo_edit_date":1774958687887,"user_edit_date":1774958687747},{"path":"frontend/src/components/ReportsPanel.jsx","record_state":"stale","record_source":"read_tool","roo_read_date":1774958701862,"roo_edit_date":1774958687887,"user_edit_date":1774958687747},{"path":"frontend/src/components/ReportsPanel.jsx","record_state":"stale","record_source":"roo_edited","roo_read_date":1774958770372,"roo_edit_date":1774958770372,"user_edit_date":1774958687747},{"path":"backend/app/main.py","record_state":"active","record_source":"roo_edited","roo_read_date":1774958905096,"roo_edit_date":1774958905096,"user_edit_date":null},{"path":"backend/app/schemas.py","record_state":"stale","record_source":"roo_edited","roo_read_date":1774958921212,"roo_edit_date":1774958921212,"user_edit_date":null},{"path":"backend/app/schemas.py","record_state":"stale","record_source":"roo_edited","roo_read_date":1774958937129,"roo_edit_date":1774958937129,"user_edit_date":null},{"path":"backend/app/schemas.py","record_state":"active","record_source":"roo_edited","roo_read_date":1774959019364,"roo_edit_date":1774959019364,"user_edit_date":null},{"path":"frontend/src/components/ReportsPanel.jsx","record_state":"stale","record_source":"read_tool","roo_read_date":1774959082914,"roo_edit_date":1774958770372,"user_edit_date":1774958687747},{"path":"frontend/src/components/ReportsPanel.jsx","record_state":"stale","record_source":"roo_edited","roo_read_date":1774959131802,"roo_edit_date":1774959131802,"user_edit_date":1774958687747},{"path":"frontend/src/components/ReportsPanel.jsx","record_state":"active","record_source":"roo_edited","roo_read_date":1774959213843,"roo_edit_date":1774959213843,"user_edit_date":1774958687747}]}